README.txt
setup.cfg
setup.py
collective/__init__.py
collective.orderedmultiselectwidget.egg-info/PKG-INFO
collective.orderedmultiselectwidget.egg-info/SOURCES.txt
collective.orderedmultiselectwidget.egg-info/dependency_links.txt
collective.orderedmultiselectwidget.egg-info/entry_points.txt
collective.orderedmultiselectwidget.egg-info/namespace_packages.txt
collective.orderedmultiselectwidget.egg-info/not-zip-safe
collective.orderedmultiselectwidget.egg-info/requires.txt
collective.orderedmultiselectwidget.egg-info/top_level.txt
collective/orderedmultiselectwidget/__init__.py
collective/orderedmultiselectwidget/configure.zcml
collective/orderedmultiselectwidget/interfaces.py
collective/orderedmultiselectwidget/browser/__init__.py
collective/orderedmultiselectwidget/browser/configure.zcml
collective/orderedmultiselectwidget/browser/itemswidgets.py
collective/orderedmultiselectwidget/profiles/default/browserlayer.xml
docs/CONTRIBUTORS.txt
docs/HISTORY.txt