Metadata-Version: 1.0
Name: collective.orderedmultiselectwidget
Version: 0.1
Summary: Provides SecureOrderedMultiSelectWidget which fixes an acquisition bug in OrderedMultiSelectWidget in zope.app.form.
Home-page: UNKNOWN
Author: JC Brand, Syslab.com GmbH
Author-email: brand@syslab.com
License: GPL
Keywords: orderedmultiselectwidget
Platform: UNKNOWN
Classifier: Framework :: Plone
Classifier: Framework :: Zope2
Classifier: Programming Language :: Python
Classifier: Topic :: Software Development :: Libraries :: Python Modules
Classifier: License :: OSI Approved :: GNU General Public License (GPL)
